CHANGELOG.md
codenames_parser/__init__.py
codenames_parser/board/__init__.py
codenames_parser/board/board_parser.py
codenames_parser/board/card_parser.py
codenames_parser/board/entrypoint.py
codenames_parser/board/grid_detection.py
codenames_parser/board/ocr.py
codenames_parser/board/template_search.py
codenames_parser/color_map/__init__.py
codenames_parser/color_map/color_detection.py
codenames_parser/color_map/color_map_parser.py
codenames_parser/color_map/color_translator.py
codenames_parser/color_map/entrypoint.py
codenames_parser/color_map/grid_detection.py
codenames_parser/color_map/mask.py
codenames_parser/common/__init__.py
codenames_parser/common/impr/__init__.py
codenames_parser/common/impr/align.py
codenames_parser/common/impr/color_manipulation.py
codenames_parser/common/impr/crop.py
codenames_parser/common/impr/fft.py
codenames_parser/common/impr/general.py
codenames_parser/common/impr/grid_detection.py
codenames_parser/common/impr/padding.py
codenames_parser/common/impr/perspective_correction.py
codenames_parser/common/impr/reader.py
codenames_parser/common/impr/scale.py
codenames_parser/common/impr/transform.py
codenames_parser/common/resources/__init__.py
codenames_parser/common/resources/card_template.jpg
codenames_parser/common/resources/card_template_1.jpg
codenames_parser/common/resources/card_template_2.jpg
codenames_parser/common/resources/resource_manager.py
codenames_parser/common/utils/__init__.py
codenames_parser/common/utils/base64.py
codenames_parser/common/utils/debug_util.py
codenames_parser/common/utils/errors.py
codenames_parser/common/utils/logging.py
codenames_parser/common/utils/models.py
codenames_parser/py.typed
codenames_parser-1.0.4.dist-info/METADATA
codenames_parser-1.0.4.dist-info/WHEEL
codenames_parser-1.0.4.dist-info/RECORD
