Metadata-Version: 2.1
Name: codenames-parser
Version: 1.0.4
Summary: Codenames board game pictures parsers.
Author: Asaf Kali
Author-email: asaf.kali@mail.huji.ac.il
Requires-Python: >=3.12,<4.0
Classifier: Programming Language :: Python :: 3
Classifier: Programming Language :: Python :: 3.12
Requires-Dist: codenames (>=5.2,<6.0)
Requires-Dist: matplotlib (>=3.9.2,<4.0.0)
Requires-Dist: numpy (>=2.1,<3.0)
Requires-Dist: opencv-python (>=4.10,<5.0)
Requires-Dist: platformdirs (>=4.3.6,<5.0.0)
Requires-Dist: pytesseract (>=0.3.13,<0.4.0)
Requires-Dist: requests (>=2.32.3,<3.0.0)
Requires-Dist: scikit-learn (>=1.5.2,<2.0.0)
Requires-Dist: tqdm (>=4.66.5,<5.0.0)
Project-URL: Homepage, https://github.com/asaf-kali/codenames-parser
Project-URL: Issues, https://github.com/asaf-kali/codenames-parser/issues
Project-URL: Repository, https://github.com/asaf-kali/codenames-parser
